[{"model": "catalog.genre", "pk": 1, "fields": {"name": "computer"}}, {"model": "catalog.genre", "pk": 2, "fields": {"name": "python"}}, {"model": "catalog.genre", "pk": 3, "fields": {"name": "web frame work"}}, {"model": "catalog.genre", "pk": 4, "fields": {"name": "\u6563\u6587"}}, {"model": "catalog.genre", "pk": 5, "fields": {"name": "\u5916\u8a9e"}}, {"model": "catalog.genre", "pk": 6, "fields": {"name": "test"}}, {"model": "catalog.book", "pk": 1, "fields": {"title": "practice Django", "author": 1, "summary": "with girls", "isbn": "-------------", "language": 1, "genre": [1, 2, 3]}}, {"model": "catalog.book", "pk": 2, "fields": {"title": "\u4f60\u6240\u8aaa\u7684\u4e00\u5207\u90fd\u5c07\u6210\u70ba\u5448\u5802\u8b49\u4f9b", "author": 2, "summary": "\u9019\u662f\u6211\u5f9e\u8b66\u9019\u4e9b\u5e74\u7684\u611f\u8a00\uff0c\u61c7\u8acb\u5404\u4f4d\u7528\u529b\u5206\u4eab\u8f49\u8cbc\uff0c\u611f\u8b1d\u5927\u5bb6\u652f\u6301\uff0c\u8b1d\u8b1d\u3002", "isbn": "9789864061990", "language": 1, "genre": [4]}}, {"model": "catalog.book", "pk": 3, "fields": {"title": "\u5982\u6b64\u4eba\u751f", "author": 3, "summary": "\u793e\u6703\u6697\u89d2\u7684\u7b11.\u6dda\u8207\u50b7", "isbn": "9789864061280", "language": 1, "genre": [4]}}, {"model": "catalog.book", "pk": 4, "fields": {"title": "\u5927\u5bb6\u4f86\u5b78\u6cf0\u8a9e", "author": 4, "summary": "\u6cf0\u8a9e\u5b78\u7fd2", "isbn": "9789866371387", "language": 1, "genre": [5]}}, {"model": "catalog.book", "pk": 5, "fields": {"title": "test 2", "author": 1, "summary": "test 2", "isbn": "1233456789012", "language": 2, "genre": [6]}}, {"model": "catalog.bookinstance", "pk": "04a4ad7d-6aff-4dd6-9a79-b2a1b72803f0", "fields": {"book": 2, "imprint": "v1 @kjHouse", "due_back": null, "borrower": null, "status": "a"}}, {"model": "catalog.bookinstance", "pk": "25a22795-a659-4de1-8e1b-1e8d9f0d5bc2", "fields": {"book": 4, "imprint": "\u7d71\u4e00\u51fa\u7248\u793e \u5b9a\u50f9500", "due_back": null, "borrower": null, "status": "a"}}, {"model": "catalog.bookinstance", "pk": "58b02177-18de-4bde-bf5f-a03b236c5315", "fields": {"book": 5, "imprint": "just a test", "due_back": "2021-01-01", "borrower": 1, "status": "r"}}, {"model": "catalog.author", "pk": 1, "fields": {"first_name": "k", "last_name": "j", "date_of_birth": "0001-01-01", "date_of_death": null}}, {"model": "catalog.author", "pk": 2, "fields": {"first_name": "\u9d3f", "last_name": "\u689d\u5b50", "date_of_birth": "1976-06-04", "date_of_death": null}}, {"model": "catalog.author", "pk": 3, "fields": {"first_name": "\u7acb\u9752", "last_name": "\u6797", "date_of_birth": "1985-12-05", "date_of_death": null}}, {"model": "catalog.author", "pk": 4, "fields": {"first_name": "\u541b\u677e", "last_name": "\u5f35", "date_of_birth": null, "date_of_death": null}}, {"model": "catalog.language", "pk": 1, "fields": {"name": "\u4e2d\u6587"}}, {"model": "catalog.language", "pk": 2, "fields": {"name": "English"}}]